best_rq_pytorch/__init__.py
best_rq_pytorch/attend.py
best_rq_pytorch/best_rq.py
best_rq_pytorch/conformer.py
best_rq_pytorch/data.py
best_rq_pytorch/optimizer.py
best_rq_pytorch/trainer.py
best_rq_pytorch-0.0.2.dist-info/LICENSE
best_rq_pytorch-0.0.2.dist-info/METADATA
best_rq_pytorch-0.0.2.dist-info/WHEEL
best_rq_pytorch-0.0.2.dist-info/top_level.txt
best_rq_pytorch-0.0.2.dist-info/RECORD
