Metadata-Version: 2.1
Name: best-rq-pytorch
Version: 0.0.2
Summary: BEST-RQ - Pytorch
Home-page: https://github.com/lucasnewman/best-rq-pytorch
Author: Lucas Newman
Author-email: lucasnewman@me.com
License: MIT
Keywords: artificial intelligence,asr,audio-generation,deep learning,transformers,text-to-speech
Classifier: Development Status :: 4 - Beta
Classifier: Intended Audience :: Developers
Classifier: Topic :: Scientific/Engineering :: Artificial Intelligence
Classifier: License :: OSI Approved :: MIT License
Classifier: Programming Language :: Python :: 3.9
License-File: LICENSE
Requires-Dist: beartype
Requires-Dist: einops >=0.6.1
Requires-Dist: rotary-embedding-torch >=0.3.0
Requires-Dist: torch >=2.0
Requires-Dist: torchaudio >=2.0
Requires-Dist: tqdm
Requires-Dist: vector-quantize-pytorch >=1.7.0
